{
    "Weapons": 
    {
    "Master_Sword": {
        "baseatk": 30,
        "basedurability": 40,
        "weapontype": "normal",
        "maxpossibleatk": 30,
        "maxpossibledurabilty": 40,
        "name": "Master_Sword",
        "whitebonusatkup": 0,
        "whitedurabilityup": 0,
        "yellowbonusatkup": 0,
        "yellowdurabilityup": 0,
        "weaponstyle": "onehanded"
    },
    "Master_Sword_Full_Power": {
        "baseatk": 60,
        "basedurability": 188,
        "weapontype": "normal",
        "maxpossibleatk": 60,
        "maxpossibledurabilty": 188,
        "name": "Master_Sword_(Full_Power)",
        "whitebonusatkup": 0,
        "whitedurabilityup": 0,
        "yellowbonusatkup": 0,
        "yellowdurabilityup": 0,
        "weaponstyle": "onehanded"
    },
    "Tree_Branch": {
        "baseatk": 2,
        "basedurability": 4,
        "weapontype": "normal",
        "maxpossibleatk": 4,
        "maxpossibledurabilty": 5,
        "name": "Tree_Branch",
        "whitebonusatkup": 2,
        "whitedurabilityup": 1,
        "yellowbonusatkup": 0,
        "yellowdurabilityup": 0,
        "weaponstyle": "onehanded"
    },
    "Torch": {
        "baseatk": 2,
        "basedurability": 8,
        "weapontype": "normal",
        "maxpossibleatk": 6,
        "maxpossibledurabilty": 12,
        "name": "Torch",
        "whitebonusatkup": 2,
        "whitedurabilityup": 2,
        "yellowbonusatkup": 4,
        "yellowdurabilityup": 4,
        "weaponstyle": "onehanded"
    },
    "Soup_Ladle": {
        "baseatk": 4,
        "basedurability": 5,
        "weapontype": "normal",
        "maxpossibleatk": 8,
        "maxpossibledurabilty": 6,
        "name": "Soup_Ladle",
        "whitebonusatkup": 4,
        "whitedurabilityup": 1,
        "yellowbonusatkup": 0,
        "yellowdurabilityup": 0,
        "weaponstyle": "onehanded"
    },
    "Spring_Loaded_Hammer": {
        "baseatk": 1,
        "basedurability": 80,
        "weapontype": "normal",
        "maxpossibleatk": 1,
        "maxpossibledurabilty": 80,
        "name": "Spring-Loaded_Hammer",
        "whitebonusatkup": 0,
        "whitedurabilityup": 0,
        "yellowbonusatkup": 0,
        "yellowdurabilityup": 0,
        "weaponstyle": "onehanded"
    },
    "Travelers_Sword": {
        "baseatk": 5,
        "basedurability": 20,
        "weapontype": "normal",
        "maxpossibleatk": 13,
        "maxpossibledurabilty": 23,
        "name": "Travelers_Sword",
        "whitebonusatkup": 5,
        "whitedurabilityup": 2,
        "yellowbonusatkup": 8,
        "yellowdurabilityup": 3,
        "weaponstyle": "onehanded"
    },
    "Soldiers_Broadsword": {
        "baseatk": 14,
        "basedurability": 23,
        "weapontype": "normal",
        "maxpossibleatk": 25,
        "maxpossibledurabilty": 26,
        "name": "Soldiers_Broadsword",
        "whitebonusatkup": 6,
        "whitedurabilityup": 2,
        "yellowbonusatkup": 11,
        "yellowdurabilityup": 3,
        "weaponstyle": "onehanded"
    },
    "Knights_Broadsword": {
        "baseatk": 26,
        "basedurability": 27,
        "weapontype": "normal",
        "maxpossibleatk": 35,
        "maxpossibledurabilty": 35,
        "name": "Knights_Broadsword",
        "whitebonusatkup": 5,
        "whitedurabilityup": 5,
        "yellowbonusatkup": 9,
        "yellowdurabilityup": 8,
        "weaponstyle": "onehanded"
    },
    "Royal_Broadsword": {
        "baseatk": 36,
        "basedurability": 36,
        "weapontype": "normal",
        "maxpossibleatk": 60,
        "maxpossibledurabilty": 54,
        "name": "Royal_Broadsword",
        "whitebonusatkup": 12,
        "whitedurabilityup": 9,
        "yellowbonusatkup": 24,
        "yellowdurabilityup": 18,
        "weaponstyle": "onehanded"
    },
    "Forest_Dwellers_Sword": {
        "baseatk": 22,
        "basedurability": 27,
        "weapontype": "normal",
        "maxpossibleatk": 30,
        "maxpossibledurabilty": 54,
        "name": "Forest_Dwellers_Sword",
        "whitebonusatkup": 4,
        "whitedurabilityup": 6,
        "yellowbonusatkup": 8,
        "yellowdurabilityup": 14,
        "weaponstyle": "onehanded"
    },
    "Zora_Sword": {
        "baseatk": 15,
        "basedurability": 27,
        "weapontype": "normal",
        "maxpossibleatk": 27,
        "maxpossibledurabilty": 41,
        "name": "Zora_Sword",
        "whitebonusatkup": 6,
        "whitedurabilityup": 6,
        "yellowbonusatkup": 12,
        "yellowdurabilityup": 14,
        "weaponstyle": "onehanded"
    },
    "Feathered_Edge": {
        "baseatk": 15,
        "basedurability": 27,
        "weapontype": "normal",
        "maxpossibleatk": 27,
        "maxpossibledurabilty": 41,
        "name": "Feathered_Edge",
        "whitebonusatkup": 6,
        "whitedurabilityup": 6,
        "yellowbonusatkup": 12,
        "yellowdurabilityup": 14,
        "weaponstyle": "onehanded"
    },
    "Gerudo_Scimitar": {
        "baseatk": 16,
        "basedurability": 23,
        "weapontype": "normal",
        "maxpossibleatk": 24,
        "maxpossibledurabilty": 35,
        "name": "Gerudo_Scimitar",
        "whitebonusatkup": 5,
        "whitedurabilityup": 5,
        "yellowbonusatkup": 8,
        "yellowdurabilityup": 12,
        "weaponstyle": "onehanded"
    },
    "Moonlight_Scimitar": {
        "baseatk": 25,
        "basedurability": 32,
        "weapontype": "normal",
        "maxpossibleatk": 31,
        "maxpossibledurabilty": 48,
        "name": "Moonlight_Scimitar",
        "whitebonusatkup": 4,
        "whitedurabilityup": 7,
        "yellowbonusatkup": 6,
        "yellowdurabilityup": 16,
        "weaponstyle": "onehanded"
    },
    "Scimitar_of_the_Seven": {
        "baseatk": 32,
        "basedurability": 60,
        "weapontype": "normal",
        "maxpossibleatk": 32,
        "maxpossibledurabilty": 60,
        "name": "Scimitar_of_the_Seven",
        "whitebonusatkup": 0,
        "whitedurabilityup": 0,
        "yellowbonusatkup": 0,
        "yellowdurabilityup": 0,
        "weaponstyle": "onehanded"
    },
    "Eightfold_Blade": {
        "baseatk": 15,
        "basedurability": 26,
        "weapontype": "normal",
        "maxpossibleatk": 27,
        "maxpossibledurabilty": 39,
        "name": "Eightfold_Blade",
        "whitebonusatkup": 6,
        "whitedurabilityup": 6,
        "yellowbonusatkup": 12,
        "yellowdurabilityup": 13,
        "weaponstyle": "onehanded"
    },
    "Rusty_Broadsword": {
        "baseatk": 6,
        "basedurability": 8,
        "weapontype": "normal",
        "maxpossibleatk": 16,
        "maxpossibledurabilty": 12,
        "name": "Rusty_Broadsword",
        "whitebonusatkup": 6,
        "whitedurabilityup": 2,
        "yellowbonusatkup": 10,
        "yellowdurabilityup": 4,
        "weaponstyle": "onehanded"
    },
    "Royal_Guards_Sword": {
        "baseatk": 48,
        "basedurability": 14,
        "weapontype": "normal",
        "maxpossibleatk": 81,
        "maxpossibledurabilty": 21,
        "name": "Royal_Guards_Sword",
        "whitebonusatkup": 16,
        "whitedurabilityup": 3,
        "yellowbonusatkup": 33,
        "yellowdurabilityup": 7,
        "weaponstyle": "onehanded"
    },
    "Flameblade": {
        "baseatk": 24,
        "basedurability": 36,
        "weapontype": "normal",
        "maxpossibleatk": 43,
        "maxpossibledurabilty": 54,
        "name": "Flameblade",
        "whitebonusatkup": 9,
        "whitedurabilityup": 8,
        "yellowbonusatkup": 19,
        "yellowdurabilityup": 18,
        "weaponstyle": "onehanded"
    },
    "Frostblade": {
        "baseatk": 20,
        "basedurability": 30,
        "weapontype": "normal",
        "maxpossibleatk": 36,
        "maxpossibledurabilty": 48,
        "name": "Frostblade",
        "whitebonusatkup": 8,
        "whitedurabilityup": 8,
        "yellowbonusatkup": 16,
        "yellowdurabilityup": 18,
        "weaponstyle": "onehanded"
    },
    "Thunderblade": {
        "baseatk": 22,
        "basedurability": 36,
        "weapontype": "normal",
        "maxpossibleatk": 40,
        "maxpossibledurabilty": 54,
        "name": "Thunderblade",
        "whitebonusatkup": 8,
        "whitedurabilityup": 8,
        "yellowbonusatkup": 18,
        "yellowdurabilityup": 18,
        "weaponstyle": "onehanded"
    },
    "Goddess_Sword": {
        "baseatk": 28,
        "basedurability": 45,
        "weapontype": "normal",
        "maxpossibleatk": 45,
        "maxpossibledurabilty": 68,
        "name": "Goddess_Sword_(Amiibo)",
        "whitebonusatkup": 10,
        "whitedurabilityup": 9,
        "yellowbonusatkup": 17,
        "yellowdurabilityup": 23,
        "weaponstyle": "onehanded"
    },
    "Sword": {
        "baseatk": 22,
        "basedurability": 27,
        "weapontype": "normal",
        "maxpossibleatk": 36,
        "maxpossibledurabilty": 41,
        "name": "Sword_(Amiibo)",
        "whitebonusatkup": 8,
        "whitedurabilityup": 6,
        "yellowbonusatkup": 14,
        "yellowdurabilityup": 14,
        "weaponstyle": "onehanded"
    },
    "Boko_Club": {
        "baseatk": 4,
        "basedurability": 12,
        "weapontype": "normal",
        "maxpossibleatk": 11,
        "maxpossibledurabilty": 18,
        "name": "Boko_Club",
        "whitebonusatkup": 4,
        "whitedurabilityup": 3,
        "yellowbonusatkup": 7,
        "yellowdurabilityup": 6,
        "weaponstyle": "onehanded"
    },
    "Spiked_Boko_Club": {
        "baseatk": 12,
        "basedurability": 14,
        "weapontype": "normal",
        "maxpossibleatk": 23,
        "maxpossibledurabilty": 21,
        "name": "Spiked_Boko_Club",
        "whitebonusatkup": 6,
        "whitedurabilityup": 3,
        "yellowbonusatkup": 11,
        "yellowdurabilityup": 7,
        "weaponstyle": "onehanded"
    },
    "Lynel_Sword": {
        "baseatk": 24,
        "basedurability": 26,
        "weapontype": "normal",
        "maxpossibleatk": 35,
        "maxpossibledurabilty": 39,
        "name": "Lynel_Sword",
        "whitebonusatkup": 6,
        "whitedurabilityup": 6,
        "yellowbonusatkup": 11,
        "yellowdurabilityup": 13,
        "weaponstyle": "onehanded"
    },
    "Mighty_Lynel_Sword": {
        "baseatk": 36,
        "basedurability": 32,
        "weapontype": "normal",
        "maxpossibleatk": 57,
        "maxpossibledurabilty": 48,
        "name": "Mighty_Lynel_Sword",
        "whitebonusatkup": 11,
        "whitedurabilityup": 7,
        "yellowbonusatkup": 21,
        "yellowdurabilityup": 16,
        "weaponstyle": "onehanded"
    },
    "Savage_Lynel_Sword": {
        "baseatk": 58,
        "basedurability": 41,
        "weapontype": "normal",
        "maxpossibleatk": 100,
        "maxpossibledurabilty": 62,
        "name": "Savage_Lynel_Sword",
        "whitebonusatkup": 21,
        "whitedurabilityup": 9,
        "yellowbonusatkup": 42,
        "yellowdurabilityup": 21,
        "weaponstyle": "onehanded"
    },
    "Fire_Rod": {
        "baseatk": 5,
        "basedurability": 14,
        "weapontype": "normal",
        "maxpossibleatk": 13,
        "maxpossibledurabilty": 21,
        "name": "Fire_Rod",
        "whitebonusatkup": 3,
        "whitedurabilityup": 3,
        "yellowbonusatkup": 8,
        "yellowdurabilityup": 7,
        "weaponstyle": "onehanded"
    },
    "Meteor_Rod": {
        "baseatk": 10,
        "basedurability": 32,
        "weapontype": "normal",
        "maxpossibleatk": 26,
        "maxpossibledurabilty": 48,
        "name": "Meteor_Rod",
        "whitebonusatkup": 6,
        "whitedurabilityup": 7,
        "yellowbonusatkup": 16,
        "yellowdurabilityup": 16,
        "weaponstyle": "onehanded"
    },
    "Ice_Rod": {
        "baseatk": 5,
        "basedurability": 14,
        "weapontype": "normal",
        "maxpossibleatk": 13,
        "maxpossibledurabilty": 21,
        "name": "Ice_Rod",
        "whitebonusatkup": 3,
        "whitedurabilityup": 3,
        "yellowbonusatkup": 8,
        "yellowdurabilityup": 7,
        "weaponstyle": "onehanded"
    },
    "Blizzard_Rod": {
        "baseatk": 10,
        "basedurability": 32,
        "weapontype": "normal",
        "maxpossibleatk": 26,
        "maxpossibledurabilty": 48,
        "name": "Blizzard_Rod",
        "whitebonusatkup": 6,
        "whitedurabilityup": 7,
        "yellowbonusatkup": 16,
        "yellowdurabilityup": 16,
        "weaponstyle": "onehanded"
    },
    "Lightning_Rod": {
        "baseatk": 5,
        "basedurability": 14,
        "weapontype": "normal",
        "maxpossibleatk": 13,
        "maxpossibledurabilty": 21,
        "name": "Lightning_Rod",
        "whitebonusatkup": 3,
        "whitedurabilityup": 3,
        "yellowbonusatkup": 8,
        "yellowdurabilityup": 7,
        "weaponstyle": "onehanded"
    },
    "Thunderstorm_Rod": {
        "baseatk": 10,
        "basedurability": 32,
        "weapontype": "normal",
        "maxpossibleatk": 26,
        "maxpossibledurabilty": 48,
        "name": "Thunderstorm_Rod",
        "whitebonusatkup": 6,
        "whitedurabilityup": 7,
        "yellowbonusatkup": 16,
        "yellowdurabilityup": 16,
        "weaponstyle": "onehanded"
    },
    "Vicious_Sickle": {
        "baseatk": 16,
        "basedurability": 14,
        "weapontype": "normal",
        "maxpossibleatk": 29,
        "maxpossibledurabilty": 21,
        "name": "Vicious_Sickle",
        "whitebonusatkup": 6,
        "whitedurabilityup": 3,
        "yellowbonusatkup": 13,
        "yellowdurabilityup": 7,
        "weaponstyle": "onehanded"
    },
    "Demon_Carver": {
        "baseatk": 40,
        "basedurability": 25,
        "weapontype": "normal",
        "maxpossibleatk": 67,
        "maxpossibledurabilty": 37,
        "name": "Demon_Carver",
        "whitebonusatkup": 14,
        "whitedurabilityup": 5,
        "yellowbonusatkup": 27,
        "yellowdurabilityup": 12,
        "weaponstyle": "onehanded"
    },
    "Bokoblin_Arm": {
        "baseatk": 5,
        "basedurability": 5,
        "weapontype": "normal",
        "maxpossibleatk": 5,
        "maxpossibledurabilty": 5,
        "name": "Bokoblin_Arm",
        "whitebonusatkup": 5,
        "whitedurabilityup": 5,
        "yellowbonusatkup": 5,
        "yellowdurabilityup": 5,
        "weaponstyle": "onehanded"
    },
    "Lizalfos_Arm": {
        "baseatk": 12,
        "basedurability": 8,
        "weapontype": "bone",
        "maxpossibleatk": 12,
        "maxpossibledurabilty": 8,
        "name": "Lizalfos_Arm",
        "whitebonusatkup": 12,
        "whitedurabilityup": 8,
        "yellowbonusatkup": 12,
        "yellowdurabilityup": 8,
        "weaponstyle": "onehanded"
    },
    "Korok_Leaf": {
        "baseatk": 1,
        "basedurability": 25,
        "weapontype": "normal",
        "maxpossibleatk": 1,
        "maxpossibledurabilty": 25,
        "name": "Korok_Leaf",
        "whitebonusatkup": 0,
        "whitedurabilityup": 0,
        "yellowbonusatkup": 0,
        "yellowdurabilityup": 0,
        "weaponstyle": "onehanded"
    },
    "Farming_Hoe": {
        "baseatk": 16,
        "basedurability": 6,
        "weapontype": "normal",
        "maxpossibleatk": 36,
        "maxpossibledurabilty": 9,
        "name": "Farming_Hoe",
        "whitebonusatkup": 14,
        "whitedurabilityup": 2,
        "yellowbonusatkup": 20,
        "yellowdurabilityup": 3,
        "weaponstyle": "twohanded"
    },
    "Boat_Oar": {
        "baseatk": 14,
        "basedurability": 8,
        "weapontype": "normal",
        "maxpossibleatk": 27,
        "maxpossibledurabilty": 10,
        "name": "Boat_Oar",
        "whitebonusatkup": 13,
        "whitedurabilityup": 2,
        "yellowbonusatkup": 0,
        "yellowdurabilityup": 0,
        "weaponstyle": "twohanded"
    },
    "Woodcutters_Axe": {
        "baseatk": 3,
        "basedurability": 47,
        "weapontype": "normal",
        "maxpossibleatk": 6,
        "maxpossibledurabilty": 55,
        "name": "Woodcutters_Axe",
        "whitebonusatkup": 3,
        "whitedurabilityup": 8,
        "yellowbonusatkup": 0,
        "yellowdurabilityup": 0,
        "weaponstyle": "twohanded"
    },
    "Double_Axe": {
        "baseatk": 18,
        "basedurability": 52,
        "weapontype": "normal",
        "maxpossibleatk": 40,
        "maxpossibledurabilty": 73,
        "name": "Double_Axe",
        "whitebonusatkup": 16,
        "whitedurabilityup": 9,
        "yellowbonusatkup": 22,
        "yellowdurabilityup": 21,
        "weaponstyle": "twohanded"
    },
    "Travelers_Claymore": {
        "baseatk": 10,
        "basedurability": 20,
        "weapontype": "normal",
        "maxpossibleatk": 19,
        "maxpossibledurabilty": 24,
        "name": "Travelers_Claymore",
        "whitebonusatkup": 5,
        "whitedurabilityup": 3,
        "yellowbonusatkup": 9,
        "yellowdurabilityup": 4,
        "weaponstyle": "twohanded"
    },
    "Soldiers_Claymore": {
        "baseatk": 20,
        "basedurability": 25,
        "weapontype": "normal",
        "maxpossibleatk": 37,
        "maxpossibledurabilty": 28,
        "name": "Soldiers_Claymore",
        "whitebonusatkup": 9,
        "whitedurabilityup": 2,
        "yellowbonusatkup": 17,
        "yellowdurabilityup": 3,
        "weaponstyle": "twohanded"
    },
    "Knights_Claymore": {
        "baseatk": 38,
        "basedurability": 30,
        "weapontype": "normal",
        "maxpossibleatk": 51,
        "maxpossibledurabilty": 38,
        "name": "Knights_Claymore",
        "whitebonusatkup": 7,
        "whitedurabilityup": 5,
        "yellowbonusatkup": 13,
        "yellowdurabilityup": 8,
        "weaponstyle": "twohanded"
    },
    "Royal_Claymore": {
        "baseatk": 52,
        "basedurability": 40,
        "weapontype": "normal",
        "maxpossibleatk": 72,
        "maxpossibledurabilty": 58,
        "name": "Royal_Claymore",
        "whitebonusatkup": 10,
        "whitedurabilityup": 9,
        "yellowbonusatkup": 20,
        "yellowdurabilityup": 18,
        "weaponstyle": "twohanded"
    },
    "Silver_Longsword": {
        "baseatk": 22,
        "basedurability": 30,
        "weapontype": "normal",
        "maxpossibleatk": 41,
        "maxpossibledurabilty": 44,
        "name": "Silver_Longsword",
        "whitebonusatkup": 8,
        "whitedurabilityup": 6,
        "yellowbonusatkup": 19,
        "yellowdurabilityup": 14,
        "weaponstyle": "twohanded"
    },
    "Golden_Claymore": {
        "baseatk": 28,
        "basedurability": 30,
        "weapontype": "normal",
        "maxpossibleatk": 43,
        "maxpossibledurabilty": 57,
        "name": "Golden_Claymore",
        "whitebonusatkup": 8,
        "whitedurabilityup": 11,
        "yellowbonusatkup": 15,
        "yellowdurabilityup": 27,
        "weaponstyle": "twohanded"
    },
    "Eightfold_Longblade": {
        "baseatk": 32,
        "basedurability": 25,
        "weapontype": "normal",
        "maxpossibleatk": 43,
        "maxpossibledurabilty": 37,
        "name": "Eightfold_Longblade",
        "whitebonusatkup": 6,
        "whitedurabilityup": 5,
        "yellowbonusatkup": 11,
        "yellowdurabilityup": 12,
        "weaponstyle": "twohanded"
    },
    "Edge_of_Duality": {
        "baseatk": 50,
        "basedurability": 35,
        "weapontype": "normal",
        "maxpossibleatk": 69,
        "maxpossibledurabilty": 51,
        "name": "Edge_of_Duality",
        "whitebonusatkup": 10,
        "whitedurabilityup": 7,
        "yellowbonusatkup": 19,
        "yellowdurabilityup": 16,
        "weaponstyle": "twohanded"
    },
    "Rusty_Claymore": {
        "baseatk": 12,
        "basedurability": 10,
        "weapontype": "normal",
        "maxpossibleatk": 34,
        "maxpossibledurabilty": 15,
        "name": "Rusty_Claymore",
        "whitebonusatkup": 11,
        "whitedurabilityup": 2,
        "yellowbonusatkup": 22,
        "yellowdurabilityup": 5,
        "weaponstyle": "twohanded"
    },
    "Royal_Guards_Claymore": {
        "baseatk": 72,
        "basedurability": 15,
        "weapontype": "normal",
        "maxpossibleatk": 116,
        "maxpossibledurabilty": 50,
        "name": "Royal_Guards_Claymore",
        "whitebonusatkup": 26,
        "whitedurabilityup": 8,
        "yellowbonusatkup": 44,
        "yellowdurabilityup": 35,
        "weaponstyle": "twohanded"
    },
    "Great_Flameblade": {
        "baseatk": 34,
        "basedurability": 50,
        "weapontype": "normal",
        "maxpossibleatk": 55,
        "maxpossibledurabilty": 80,
        "name": "Great_Flameblade",
        "whitebonusatkup": 12,
        "whitedurabilityup": 15,
        "yellowbonusatkup": 21,
        "yellowdurabilityup": 30,
        "weaponstyle": "twohanded"
    },
    "Great_Frostblade": {
        "baseatk": 30,
        "basedurability": 40,
        "weapontype": "normal",
        "maxpossibleatk": 48,
        "maxpossibledurabilty": 70,
        "name": "Great_Frostblade",
        "whitebonusatkup": 11,
        "whitedurabilityup": 15,
        "yellowbonusatkup": 18,
        "yellowdurabilityup": 30,
        "weaponstyle": "twohanded"
    },
    "Great_Thunderblade": {
        "baseatk": 32,
        "basedurability": 50,
        "weapontype": "normal",
        "maxpossibleatk": 52,
        "maxpossibledurabilty": 80,
        "name": "Great_Thunderblade",
        "whitebonusatkup": 12,
        "whitedurabilityup": 15,
        "yellowbonusatkup": 20,
        "yellowdurabilityup": 30,
        "weaponstyle": "twohanded"
    },
    "Sword_of_the_Six_Sages": {
        "baseatk": 48,
        "basedurability": 50,
        "weapontype": "normal",
        "maxpossibleatk": 67,
        "maxpossibledurabilty": 93,
        "name": "Sword_of_the_Six_Sages_(Amiibo)",
        "whitebonusatkup": 10,
        "whitedurabilityup": 25,
        "yellowbonusatkup": 19,
        "yellowdurabilityup": 43,
        "weaponstyle": "twohanded"
    },
    "Biggorons_Sword": {
        "baseatk": 50,
        "basedurability": 60,
        "weapontype": "normal",
        "maxpossibleatk": 69,
        "maxpossibledurabilty": 111,
        "name": "Biggorons_Sword_(Amiibo)",
        "whitebonusatkup": 10,
        "whitedurabilityup": 30,
        "yellowbonusatkup": 19,
        "yellowdurabilityup": 51,
        "weaponstyle": "twohanded"
    },
    "Fierce_Deity_Sword": {
        "baseatk": 60,
        "basedurability": 35,
        "weapontype": "normal",
        "maxpossibleatk": 83,
        "maxpossibledurabilty": 65,
        "name": "Fierce_Deity_Sword_(Amiibo)",
        "whitebonusatkup": 12,
        "whitedurabilityup": 18,
        "yellowbonusatkup": 23,
        "yellowdurabilityup": 30,
        "weaponstyle": "twohanded"
    },
    "Boko_Bat": {
        "baseatk": 6,
        "basedurability": 8,
        "weapontype": "normal",
        "maxpossibleatk": 17,
        "maxpossibledurabilty": 12,
        "name": "Boko_Bat",
        "whitebonusatkup": 6,
        "whitedurabilityup": 2,
        "yellowbonusatkup": 11,
        "yellowdurabilityup": 4,
        "weaponstyle": "twohanded"
    },
    "Spiked_Boko_Bat": {
        "baseatk": 18,
        "basedurability": 12,
        "weapontype": "normal",
        "maxpossibleatk": 35,
        "maxpossibledurabilty": 18,
        "name": "Spiked_Boko_Bat",
        "whitebonusatkup": 9,
        "whitedurabilityup": 3,
        "yellowbonusatkup": 17,
        "yellowdurabilityup": 6,
        "weaponstyle": "twohanded"
    },
    "Moblin_Club": {
        "baseatk": 9,
        "basedurability": 12,
        "weapontype": "normal",
        "maxpossibleatk": 26,
        "maxpossibledurabilty": 18,
        "name": "Moblin_Club",
        "whitebonusatkup": 9,
        "whitedurabilityup": 3,
        "yellowbonusatkup": 17,
        "yellowdurabilityup": 6,
        "weaponstyle": "twohanded"
    },
    "Spiked_Moblin_Club": {
        "baseatk": 27,
        "basedurability": 18,
        "weapontype": "normal",
        "maxpossibleatk": 44,
        "maxpossibledurabilty": 27,
        "name": "Spiked_Moblin_Club",
        "whitebonusatkup": 9,
        "whitedurabilityup": 4,
        "yellowbonusatkup": 17,
        "yellowdurabilityup": 9,
        "weaponstyle": "twohanded"
    },
    "Lynel_Crusher": {
        "baseatk": 36,
        "basedurability": 20,
        "weapontype": "normal",
        "maxpossibleatk": 53,
        "maxpossibledurabilty": 29,
        "name": "Lynel_Crusher",
        "whitebonusatkup": 9,
        "whitedurabilityup": 4,
        "yellowbonusatkup": 17,
        "yellowdurabilityup": 9,
        "weaponstyle": "twohanded"
    },
    "Mighty_Lynel_Crusher": {
        "baseatk": 54,
        "basedurability": 25,
        "weapontype": "normal",
        "maxpossibleatk": 77,
        "maxpossibledurabilty": 37,
        "name": "Mighty_Lynel_Crusher",
        "whitebonusatkup": 12,
        "whitedurabilityup": 5,
        "yellowbonusatkup": 23,
        "yellowdurabilityup": 12,
        "weaponstyle": "twohanded"
    },
    "Savage_Lynel_Crusher": {
        "baseatk": 78,
        "basedurability": 35,
        "weapontype": "normal",
        "maxpossibleatk": 108,
        "maxpossibledurabilty": 51,
        "name": "Savage_Lynel_Crusher",
        "whitebonusatkup": 15,
        "whitedurabilityup": 7,
        "yellowbonusatkup": 30,
        "yellowdurabilityup": 16,
        "weaponstyle": "twohanded"
    },
    "Windcleaver": {
        "baseatk": 40,
        "basedurability": 25,
        "weapontype": "normal",
        "maxpossibleatk": 54,
        "maxpossibledurabilty": 49,
        "name": "Windcleaver",
        "whitebonusatkup": 8,
        "whitedurabilityup": 15,
        "yellowbonusatkup": 14,
        "yellowdurabilityup": 24,
        "weaponstyle": "twohanded"
    },
    "Moblin_Arm": {
        "baseatk": 15,
        "basedurability": 5,
        "weapontype": "bone",
        "maxpossibleatk": 15,
        "maxpossibledurabilty": 5,
        "name": "Moblin_Arm",
        "whitebonusatkup": 0,
        "whitedurabilityup": 0,
        "yellowbonusatkup": 0,
        "yellowdurabilityup": 0,
        "weaponstyle": "twohanded"
    },
    "Wooden_Mop": {
        "baseatk": 5,
        "basedurability": 8,
        "weapontype": "normal",
        "maxpossibleatk": 9,
        "maxpossibledurabilty": 10,
        "name": "Wooden_Mop",
        "whitebonusatkup": 4,
        "whitedurabilityup": 2,
        "yellowbonusatkup": 0,
        "yellowdurabilityup": 0,
        "weaponstyle": "spear"
    },
    "Farmers_Pitchfork": {
        "baseatk": 7,
        "basedurability": 12,
        "weapontype": "normal",
        "maxpossibleatk": 7,
        "maxpossibledurabilty": 12,
        "name": "Farmers_Pitchfork",
        "whitebonusatkup": 0,
        "whitedurabilityup": 0,
        "yellowbonusatkup": 0,
        "yellowdurabilityup": 0,
        "weaponstyle": "spear"
    },
    "Fishing_Harpoon": {
        "baseatk": 8,
        "basedurability": 12,
        "weapontype": "normal",
        "maxpossibleatk": 14,
        "maxpossibledurabilty": 18,
        "name": "Fishing_Harpoon",
        "whitebonusatkup": 4,
        "whitedurabilityup": 3,
        "yellowbonusatkup": 6,
        "yellowdurabilityup": 6,
        "weaponstyle": "spear"
    },
    "Throwing_Spear": {
        "baseatk": 6,
        "basedurability": 20,
        "weapontype": "normal",
        "maxpossibleatk": 18,
        "maxpossibledurabilty": 29,
        "name": "Throwing_Spear",
        "whitebonusatkup": 6,
        "whitedurabilityup": 4,
        "yellowbonusatkup": 12,
        "yellowdurabilityup": 9,
        "weaponstyle": "spear"
    },
    "Travelers_Spear": {
        "baseatk": 3,
        "basedurability": 30,
        "weapontype": "normal",
        "maxpossibleatk": 6,
        "maxpossibledurabilty": 34,
        "name": "Travelers_Spear",
        "whitebonusatkup": 2,
        "whitedurabilityup": 3,
        "yellowbonusatkup": 3,
        "yellowdurabilityup": 4,
        "weaponstyle": "spear"
    },
    "Soldiers_Spear": {
        "baseatk": 7,
        "basedurability": 35,
        "weapontype": "normal",
        "maxpossibleatk": 12,
        "maxpossibledurabilty": 38,
        "name": "Soldiers_Spear",
        "whitebonusatkup": 3,
        "whitedurabilityup": 2,
        "yellowbonusatkup": 5,
        "yellowdurabilityup": 3,
        "weaponstyle": "spear"
    },
    "Knights_Halberd": {
        "baseatk": 13,
        "basedurability": 40,
        "weapontype": "normal",
        "maxpossibleatk": 25,
        "maxpossibledurabilty": 48,
        "name": "Knights_Halberd",
        "whitebonusatkup": 7,
        "whitedurabilityup": 5,
        "yellowbonusatkup": 12,
        "yellowdurabilityup": 8,
        "weaponstyle": "spear"
    },
    "Royal_Halberd": {
        "baseatk": 26,
        "basedurability": 50,
        "weapontype": "normal",
        "maxpossibleatk": 46,
        "maxpossibledurabilty": 65,
        "name": "Royal_Halberd",
        "whitebonusatkup": 10,
        "whitedurabilityup": 8,
        "yellowbonusatkup": 20,
        "yellowdurabilityup": 15,
        "weaponstyle": "spear"
    },
    "Forest_Dwellers_Spear": {
        "baseatk": 11,
        "basedurability": 35,
        "weapontype": "normal",
        "maxpossibleatk": 22,
        "maxpossibledurabilty": 51,
        "name": "Forest_Dwellers_Spear",
        "whitebonusatkup": 6,
        "whitedurabilityup": 7,
        "yellowbonusatkup": 11,
        "yellowdurabilityup": 16,
        "weaponstyle": "spear"
    },
    "Zora_Spear": {
        "baseatk": 9,
        "basedurability": 40,
        "weapontype": "normal",
        "maxpossibleatk": 16,
        "maxpossibledurabilty": 58,
        "name": "Zora_Spear",
        "whitebonusatkup": 4,
        "whitedurabilityup": 8,
        "yellowbonusatkup": 7,
        "yellowdurabilityup": 18,
        "weaponstyle": "spear"
    },
    "Silverscale_Spear": {
        "baseatk": 12,
        "basedurability": 40,
        "weapontype": "normal",
        "maxpossibleatk": 24,
        "maxpossibledurabilty": 58,
        "name": "Silverscale_Spear",
        "whitebonusatkup": 7,
        "whitedurabilityup": 8,
        "yellowbonusatkup": 12,
        "yellowdurabilityup": 18,
        "weaponstyle": "spear"
    },
    "Ceremonial_Trident": {
        "baseatk": 14,
        "basedurability": 40,
        "weapontype": "normal",
        "maxpossibleatk": 14,
        "maxpossibledurabilty": 40,
        "name": "Ceremonial_Trident",
        "whitebonusatkup": 0,
        "whitedurabilityup": 0,
        "yellowbonusatkup": 0,
        "yellowdurabilityup": 0,
        "weaponstyle": "spear"
    },
    "Lightscale_Trident": {
        "baseatk": 22,
        "basedurability": 70,
        "weapontype": "normal",
        "maxpossibleatk": 22,
        "maxpossibledurabilty": 70,
        "name": "Lightscale_Trident",
        "whitebonusatkup": 0,
        "whitedurabilityup": 0,
        "yellowbonusatkup": 0,
        "yellowdurabilityup": 0,
        "weaponstyle": "spear"
    },
    "Drillshaft": {
        "baseatk": 14,
        "basedurability": 50,
        "weapontype": "normal",
        "maxpossibleatk": 27,
        "maxpossibledurabilty": 73,
        "name": "Drillshaft",
        "whitebonusatkup": 8,
        "whitedurabilityup": 9,
        "yellowbonusatkup": 13,
        "yellowdurabilityup": 23,
        "weaponstyle": "spear"
    },
    "Feathered_Spear": {
        "baseatk": 10,
        "basedurability": 35,
        "weapontype": "normal",
        "maxpossibleatk": 18,
        "maxpossibledurabilty": 51,
        "name": "Feathered_Spear",
        "whitebonusatkup": 5,
        "whitedurabilityup": 7,
        "yellowbonusatkup": 8,
        "yellowdurabilityup": 16,
        "weaponstyle": "spear"
    },
    "Gerudo_Spear": {
        "baseatk": 16,
        "basedurability": 35,
        "weapontype": "normal",
        "maxpossibleatk": 31,
        "maxpossibledurabilty": 51,
        "name": "Gerudo_Spear",
        "whitebonusatkup": 9,
        "whitedurabilityup": 7,
        "yellowbonusatkup": 15,
        "yellowdurabilityup": 16,
        "weaponstyle": "spear"
    },
    "Serpentine_Spear": {
        "baseatk": 12,
        "basedurability": 35,
        "weapontype": "normal",
        "maxpossibleatk": 24,
        "maxpossibledurabilty": 51,
        "name": "Serpentine_Spear",
        "whitebonusatkup": 7,
        "whitedurabilityup": 7,
        "yellowbonusatkup": 12,
        "yellowdurabilityup": 16,
        "weaponstyle": "spear"
    },
    "Rusty_Halberd": {
        "baseatk": 5,
        "basedurability": 15,
        "weapontype": "normal",
        "maxpossibleatk": 15,
        "maxpossibledurabilty": 22,
        "name": "Rusty_Halberd",
        "whitebonusatkup": 5,
        "whitedurabilityup": 3,
        "yellowbonusatkup": 10,
        "yellowdurabilityup": 7,
        "weaponstyle": "spear"
    },
    "Royal_Guards_Spear": {
        "baseatk": 32,
        "basedurability": 15,
        "weapontype": "normal",
        "maxpossibleatk": 57,
        "maxpossibledurabilty": 22,
        "name": "Royal_Guards_Spear",
        "whitebonusatkup": 13,
        "whitedurabilityup": 3,
        "yellowbonusatkup": 25,
        "yellowdurabilityup": 7,
        "weaponstyle": "spear"
    },
    "Flamespear": {
        "baseatk": 24,
        "basedurability": 50,
        "weapontype": "normal",
        "maxpossibleatk": 43,
        "maxpossibledurabilty": 73,
        "name": "Flamespear",
        "whitebonusatkup": 10,
        "whitedurabilityup": 9,
        "yellowbonusatkup": 19,
        "yellowdurabilityup": 23,
        "weaponstyle": "spear"
    },
    "Frostspear": {
        "baseatk": 20,
        "basedurability": 40,
        "weapontype": "normal",
        "maxpossibleatk": 36,
        "maxpossibledurabilty": 63,
        "name": "Frostspear",
        "whitebonusatkup": 8,
        "whitedurabilityup": 9,
        "yellowbonusatkup": 16,
        "yellowdurabilityup": 23,
        "weaponstyle": "spear"
    },
    "Thunderspear": {
        "baseatk": 22,
        "basedurability": 50,
        "weapontype": "normal",
        "maxpossibleatk": 40,
        "maxpossibledurabilty": 73,
        "name": "Thunderspear",
        "whitebonusatkup": 9,
        "whitedurabilityup": 9,
        "yellowbonusatkup": 18,
        "yellowdurabilityup": 23,
        "weaponstyle": "spear"
    },
    "Boko_Spear": {
        "baseatk": 2,
        "basedurability": 12,
        "weapontype": "normal",
        "maxpossibleatk": 5,
        "maxpossibledurabilty": 18,
        "name": "Boko_Spear",
        "whitebonusatkup": 2,
        "whitedurabilityup": 3,
        "yellowbonusatkup": 3,
        "yellowdurabilityup": 6,
        "weaponstyle": "spear"
    },
    "Spiked_Boko_Spear": {
        "baseatk": 6,
        "basedurability": 15,
        "weapontype": "normal",
        "maxpossibleatk": 11,
        "maxpossibledurabilty": 22,
        "name": "Spiked_Boko_Spear",
        "whitebonusatkup": 3,
        "whitedurabilityup": 3,
        "yellowbonusatkup": 5,
        "yellowdurabilityup": 7,
        "weaponstyle": "spear"
    },
    "Moblin_Spear": {
        "baseatk": 4,
        "basedurability": 15,
        "weapontype": "normal",
        "maxpossibleatk": 8,
        "maxpossibledurabilty": 22,
        "name": "Moblin_Spear",
        "whitebonusatkup": 3,
        "whitedurabilityup": 3,
        "yellowbonusatkup": 4,
        "yellowdurabilityup": 7,
        "weaponstyle": "spear"
    },
    "Spiked_Moblin_Spear": {
        "baseatk": 9,
        "basedurability": 20,
        "weapontype": "normal",
        "maxpossibleatk": 14,
        "maxpossibledurabilty": 29,
        "name": "Spiked_Moblin_Spear",
        "whitebonusatkup": 3,
        "whitedurabilityup": 4,
        "yellowbonusatkup": 5,
        "yellowdurabilityup": 9,
        "weaponstyle": "spear"
    },
    "Lizal_Spear": {
        "baseatk": 7,
        "basedurability": 18,
        "weapontype": "normal",
        "maxpossibleatk": 11,
        "maxpossibledurabilty": 27,
        "name": "Lizal_Spear",
        "whitebonusatkup": 3,
        "whitedurabilityup": 4,
        "yellowbonusatkup": 4,
        "yellowdurabilityup": 9,
        "weaponstyle": "spear"
    },
    "Enhanced_Lizal_Spear": {
        "baseatk": 12,
        "basedurability": 22,
        "weapontype": "normal",
        "maxpossibleatk": 17,
        "maxpossibledurabilty": 32,
        "name": "Enhanced_Lizal_Spear",
        "whitebonusatkup": 3,
        "whitedurabilityup": 7,
        "yellowbonusatkup": 5,
        "yellowdurabilityup": 10,
        "weaponstyle": "spear"
    },
    "Forked_Lizal_Spear": {
        "baseatk": 18,
        "basedurability": 28,
        "weapontype": "normal",
        "maxpossibleatk": 25,
        "maxpossibledurabilty": 41,
        "name": "Forked_Lizal_Spear",
        "whitebonusatkup": 4,
        "whitedurabilityup": 6,
        "yellowbonusatkup": 7,
        "yellowdurabilityup": 13,
        "weaponstyle": "spear"
    },
    "Lynel_Spear": {
        "baseatk": 14,
        "basedurability": 25,
        "weapontype": "normal",
        "maxpossibleatk": 19,
        "maxpossibledurabilty": 37,
        "name": "Lynel_Spear",
        "whitebonusatkup": 3,
        "whitedurabilityup": 5,
        "yellowbonusatkup": 5,
        "yellowdurabilityup": 12,
        "weaponstyle": "spear"
    },
    "Mighty_Lynel_Spear": {
        "baseatk": 20,
        "basedurability": 35,
        "weapontype": "normal",
        "maxpossibleatk": 29,
        "maxpossibledurabilty": 51,
        "name": "Mighty_Lynel_Spear",
        "whitebonusatkup": 5,
        "whitedurabilityup": 7,
        "yellowbonusatkup": 9,
        "yellowdurabilityup": 16,
        "weaponstyle": "spear"
    },
    "Savage_Lynel_Spear": {
        "baseatk": 30,
        "basedurability": 45,
        "weapontype": "normal",
        "maxpossibleatk": 44,
        "maxpossibledurabilty": 66,
        "name": "Savage_Lynel_Spear",
        "whitebonusatkup": 7,
        "whitedurabilityup": 9,
        "yellowbonusatkup": 14,
        "yellowdurabilityup": 21,
        "weaponstyle": "spear"
    },
    "Dragonbone_Boko_Spear": {
        "baseatk": 12,
        "basedurability": 20,
        "weapontype": "bone",
        "maxpossibleatk": 19,
        "maxpossibledurabilty": 29,
        "name": "Dragonbone_Boko_Spear",
        "whitebonusatkup": 4,
        "whitedurabilityup": 4,
        "yellowbonusatkup": 7,
        "yellowdurabilityup": 9,
        "weaponstyle": "spear"
    },
    "Dragonbone_Moblin_Spear": {
        "baseatk": 15,
        "basedurability": 25,
        "weapontype": "bone",
        "maxpossibleatk": 22,
        "maxpossibledurabilty": 37,
        "name": "Dragonbone_Moblin_Spear",
        "whitebonusatkup": 4,
        "whitedurabilityup": 5,
        "yellowbonusatkup": 7,
        "yellowdurabilityup": 12,
        "weaponstyle": "spear"
    },
    "Dragonbone_Boko_Bat": {
        "baseatk": 36,
        "basedurability": 16,
        "weapontype": "bone",
        "maxpossibleatk": 60,
        "maxpossibledurabilty": 24,
        "name": "Dragonbone_Boko_Bat",
        "whitebonusatkup": 12,
        "whitedurabilityup": 3,
        "yellowbonusatkup": 24,
        "yellowdurabilityup": 8,
        "weaponstyle": "twohanded"
    },
    "Dragonbone_Moblin_Club": {
        "baseatk": 45,
        "basedurability": 24,
        "weapontype": "bone",
        "maxpossibleatk": 65,
        "maxpossibledurabilty": 35,
        "name": "Dragonbone_Moblin_Club",
        "whitebonusatkup": 10,
        "whitedurabilityup": 5,
        "yellowbonusatkup": 20,
        "yellowdurabilityup": 11,
        "weaponstyle": "twohanded"
    },
    "Guardian_Sword": {
        "baseatk": 20,
        "basedurability": 17,
        "weapontype": "ancient",
        "maxpossibleatk": 29,
        "maxpossibledurabilty": 26,
        "name": "Guardian_Sword",
        "whitebonusatkup": 5,
        "whitedurabilityup": 4,
        "yellowbonusatkup": 9,
        "yellowdurabilityup": 9,
        "weaponstyle": "onehanded"
    },
    "Guardian_Sword2": {
        "baseatk": 30,
        "basedurability": 26,
        "weapontype": "ancient",
        "maxpossibleatk": 39,
        "maxpossibledurabilty": 39,
        "name": "Guardian_Sword+",
        "whitebonusatkup": 5,
        "whitedurabilityup": 6,
        "yellowbonusatkup": 9,
        "yellowdurabilityup": 13,
        "weaponstyle": "onehanded"
    },
    "Guardian_Sword3": {
        "baseatk": 40,
        "basedurability": 32,
        "weapontype": "ancient",
        "maxpossibleatk": 60,
        "maxpossibledurabilty": 48,
        "name": "Guardian_Sword++",
        "whitebonusatkup": 10,
        "whitedurabilityup": 7,
        "yellowbonusatkup": 20,
        "yellowdurabilityup": 16,
        "weaponstyle": "onehanded"
    },
    "Guardian_Spear": {
        "baseatk": 10,
        "basedurability": 20,
        "weapontype": "ancient",
        "maxpossibleatk": 14,
        "maxpossibledurabilty": 29,
        "name": "Guardian_Spear",
        "whitebonusatkup": 3,
        "whitedurabilityup": 4,
        "yellowbonusatkup": 4,
        "yellowdurabilityup": 9,
        "weaponstyle": "spear"
    },
    "Guardian_Spear2": {
        "baseatk": 15,
        "basedurability": 25,
        "weapontype": "ancient",
        "maxpossibleatk": 19,
        "maxpossibledurabilty": 37,
        "name": "Guardian_Spear+",
        "whitebonusatkup": 3,
        "whitedurabilityup": 5,
        "yellowbonusatkup": 4,
        "yellowdurabilityup": 12,
        "weaponstyle": "spear"
    },
    "Guardian_Spear3": {
        "baseatk": 20,
        "basedurability": 35,
        "weapontype": "ancient",
        "maxpossibleatk": 28,
        "maxpossibledurabilty": 51,
        "name": "Guardian_Spear++",
        "whitebonusatkup": 4,
        "whitedurabilityup": 7,
        "yellowbonusatkup": 8,
        "yellowdurabilityup": 16,
        "weaponstyle": "spear"
    },
    "Ancient_Battle_Axe": {
        "baseatk": 30,
        "basedurability": 15,
        "weapontype": "ancient",
        "maxpossibleatk": 44,
        "maxpossibledurabilty": 22,
        "name": "Ancient_Battle_Axe",
        "whitebonusatkup": 8,
        "whitedurabilityup": 3,
        "yellowbonusatkup": 14,
        "yellowdurabilityup": 7,
        "weaponstyle": "twohanded"
    },
    "Ancient_Battle_Axe2": {
        "baseatk": 45,
        "basedurability": 20,
        "weapontype": "ancient",
        "maxpossibleatk": 59,
        "maxpossibledurabilty": 29,
        "name": "Ancient_Battle_Axe+",
        "whitebonusatkup": 8,
        "whitedurabilityup": 4,
        "yellowbonusatkup": 14,
        "yellowdurabilityup": 9,
        "weaponstyle": "twohanded"
    },
    "Ancient_Battle_Axe3": {
        "baseatk": 60,
        "basedurability": 25,
        "weapontype": "ancient",
        "maxpossibleatk": 75,
        "maxpossibledurabilty": 37,
        "name": "Ancient_Battle_Axe++",
        "whitebonusatkup": 8,
        "whitedurabilityup": 5,
        "yellowbonusatkup": 15,
        "yellowdurabilityup": 12,
        "weaponstyle": "twohanded"
    },
    "Giant_Boomerang": {
        "baseatk": 25,
        "basedurability": 40,
        "weapontype": "boomerang",
        "maxpossibleatk": 47,
        "maxpossibledurabilty": 58,
        "name": "Giant_Boomerang",
        "whitebonusatkup": 11,
        "whitedurabilityup": 8,
        "yellowbonusatkup": 22,
        "yellowdurabilityup": 18,
        "weaponstyle": "twohanded"
    },
    "Lizal_Boomerang": {
        "baseatk": 14,
        "basedurability": 17,
        "weapontype": "boomerang",
        "maxpossibleatk": 23,
        "maxpossibledurabilty": 26,
        "name": "Lizal_Boomerang",
        "whitebonusatkup": 5,
        "whitedurabilityup": 4,
        "yellowbonusatkup": 9,
        "yellowdurabilityup": 9,
        "weaponstyle": "twohanded"
    },
    "Lizal_Forked_Boomerang": {
        "baseatk": 24,
        "basedurability": 23,
        "weapontype": "boomerang",
        "maxpossibleatk": 35,
        "maxpossibledurabilty": 35,
        "name": "Lizal_Forked_Boomerang",
        "whitebonusatkup": 6,
        "whitedurabilityup": 5,
        "yellowbonusatkup": 11,
        "yellowdurabilityup": 12,
        "weaponstyle": "onehanded"
    },
    "Lizal_Tri_Boomerang": {
        "baseatk": 36,
        "basedurability": 27,
        "weapontype": "boomerang",
        "maxpossibleatk": 60,
        "maxpossibledurabilty": 41,
        "name": "Lizal_Tri_Boomerang",
        "whitebonusatkup": 12,
        "whitedurabilityup": 6,
        "yellowbonusatkup": 24,
        "yellowdurabilityup": 14,
        "weaponstyle": "onehanded"
    },
    "Boomerang": {
        "baseatk": 8,
        "basedurability": 18,
        "weapontype": "boomerang",
        "maxpossibleatk": 21,
        "maxpossibledurabilty": 27,
        "name": "Boomerang",
        "whitebonusatkup": 8,
        "whitedurabilityup": 4,
        "yellowbonusatkup": 13,
        "yellowdurabilityup": 9,
        "weaponstyle": "onehanded"
    },
    "Sea_Breeze_Boomerang": {
        "baseatk": 20,
        "basedurability": 20,
        "weapontype": "boomerang",
        "maxpossibleatk": 32,
        "maxpossibledurabilty": 30,
        "name": "Sea_Breeze_Boomerang_(Amiibo)",
        "whitebonusatkup": 7,
        "whitedurabilityup": 4,
        "yellowbonusatkup": 12,
        "yellowdurabilityup": 10,
        "weaponstyle": "onehanded"
    },
    "Cobble_Crusher": {
        "baseatk": 15,
        "basedurability": 30,
        "weapontype": "mining",
        "maxpossibleatk": 41,
        "maxpossibledurabilty": 44,
        "name": "Cobble_Crusher",
        "whitebonusatkup": 14,
        "whitedurabilityup": 6,
        "yellowbonusatkup": 26,
        "yellowdurabilityup": 14,
        "weaponstyle": "twohanded"
    },
    "Stone_Smasher": {
        "baseatk": 42,
        "basedurability": 40,
        "weapontype": "mining",
        "maxpossibleatk": 59,
        "maxpossibledurabilty": 58,
        "name": "Stone_Smasher",
        "whitebonusatkup": 9,
        "whitedurabilityup": 8,
        "yellowbonusatkup": 17,
        "yellowdurabilityup": 18,
        "weaponstyle": "twohanded"
    },
    "Boulder_Breaker": {
        "baseatk": 60,
        "basedurability": 60,
        "weapontype": "mining",
        "maxpossibleatk": 60,
        "maxpossibledurabilty": 60,
        "name": "Boulder_Breaker",
        "whitebonusatkup": 0,
        "whitedurabilityup": 0,
        "yellowbonusatkup": 0,
        "yellowdurabilityup": 0,
        "weaponstyle": "twohanded"
    },
    "Iron_Sledgehammer": {
        "baseatk": 12,
        "basedurability": 40,
        "weapontype": "mining",
        "maxpossibleatk": 34,
        "maxpossibledurabilty": 58,
        "name": "Iron_Sledgehammer",
        "whitebonusatkup": 11,
        "whitedurabilityup": 8,
        "yellowbonusatkup": 22,
        "yellowdurabilityup": 18,
        "weaponstyle": "twohanded"
    },
    "Ancient_Spear": {
        "baseatk": 30,
        "basedurability": 50,
        "weapontype": "robbie",
        "maxpossibleatk": 30,
        "maxpossibledurabilty": 50,
        "name": "Ancient_Spear",
        "whitebonusatkup": 0,
        "whitedurabilityup": 0,
        "yellowbonusatkup": 0,
        "yellowdurabilityup": 0,
        "weaponstyle": "spear"
    },
    "Ancient_Bladesaw": {
        "baseatk": 55,
        "basedurability": 50,
        "weapontype": "robbie",
        "maxpossibleatk": 55,
        "maxpossibledurabilty": 50,
        "name": "Ancient_Bladesaw",
        "whitebonusatkup": 0,
        "whitedurabilityup": 0,
        "yellowbonusatkup": 0,
        "yellowdurabilityup": 0,
        "weaponstyle": "twohanded"
    },
    "Ancient_Short_Sword": {
        "baseatk": 40,
        "basedurability": 54,
        "weapontype": "robbie",
        "maxpossibleatk": 40,
        "maxpossibledurabilty": 54,
        "name": "Ancient_Short_Sword",
        "whitebonusatkup": 0,
        "whitedurabilityup": 0,
        "yellowbonusatkup": 0,
        "yellowdurabilityup": 0,
        "weaponstyle": "onehanded"
    }
}

}

